mara_cli/__init__.py
mara_cli/_config.py
mara_cli/cli.py
mara_cli-0.3.1.dist-info/LICENSE
mara_cli-0.3.1.dist-info/METADATA
mara_cli-0.3.1.dist-info/WHEEL
mara_cli-0.3.1.dist-info/entry_points.txt
mara_cli-0.3.1.dist-info/top_level.txt
mara_cli-0.3.1.dist-info/RECORD
