Metadata-Version: 2.1
Name: mara-cli
Version: 0.3.1
Summary: Mara cli app which calls the appropriate contributed subcommand.
Home-page: https://github.com/mara/mara-cli
Author: Mara contributors
License: MIT
License-File: LICENSE
Requires-Dist: click
Requires-Dist: setuptools
Provides-Extra: test
Requires-Dist: pytest ; extra == 'test'
Requires-Dist: pytest-click ; extra == 'test'
